FLIPFLOPS/JK_flipflop/jk.v
// JK Flip-Flop Module
module jk_flipflop (
    input J,        // Input J
    input K,        // Input K
    input clk,      // Clock input
    input rst,      // Asynchronous Reset
    output reg Q,   // Output Q
    output reg Qn   // Output Qn (Q not)
);
    always @(posedge clk or posedge rst) begin
        if (rst) begin
            Q <= 0;
            Qn <= 1;
        end else begin
            case ({J, K})
                2'b00: begin
                    Q <= Q;
                    Qn <= Qn;
                end
                2'b01: begin
                    Q <= 0;
                    Qn <= 1;
                end
                2'b10: begin
                    Q <= 1;
                    Qn <= 0;
                end
                2'b11: begin
                    Q <= ~Q;
                    Qn <= ~Qn;
                end
            endcase
        end
    end
endmodule

FLIPFLOPS/JK_flipflop/jk_tb.v
// Testbench for JK Flip-Flop with VCD generation
module tb_jk_flipflop;
    // Signals for JK Flip-Flop
    reg J, K, clk, rst;
    wire Q, Qn;

    // Instantiate the JK Flip-Flop
    jk_flipflop uut (
        .J(J),
        .K(K),
        .clk(clk),
        .rst(rst),
        .Q(Q),
        .Qn(Qn)
    );

    // Clock generation
    always begin
        #5 clk = ~clk; // Generate clock with 10-time unit period
    end

    // VCD file generation
    initial begin
        // Initialize signals
        clk = 0;
        rst = 0;
        J = 0;
        K = 0;

        // Open VCD file
        $dumpfile("jk_waveform.vcd");
        $dumpvars(0, tb_jk_flipflop);

        // Apply reset
        rst = 1; #10;
        rst = 0; #10;

        // Test JK Flip-Flop behavior
        J = 1; K = 0; #20; // Set J=1, K=0
        J = 0; K = 1; #20; // Set J=0, K=1
        J = 1; K = 1; #20; // Set J=1, K=1
        J = 0; K = 0; #20; // Set J=0, K=0

        // Finish the simulation
        $finish;
    end
endmodule

FLIPFLOPS/JK_flipflop/jk_waveform.vcd
$date
	Tue Mar 18 11:01:23 2025
$end
$version
	Icarus Verilog
$end
$timescale
	1s
$end
$scope module tb_jk_flipflop $end
$var wire 1 ! Qn $end
$var wire 1 " Q $end
$var reg 1 # J $end
$var reg 1 $ K $end
$var reg 1 % clk $end
$var reg 1 & rst $end
$scope module uut $end
$var wire 1 # J $end
$var wire 1 $ K $end
$var wire 1 % clk $end
$var wire 1 & rst $end
$var reg 1 " Q $end
$var reg 1 ! Qn $end
$upscope $end
$upscope $end
$enddefinitions $end
$comment Show the parameter values. $end
$dumpall
$end
#0
$dumpvars
1&
0%
0$
0#
0"
1!
$end
#5
1%
#10
0%
0&
#15
1%
#20
0%
1#
#25
0!
1"
1%
#30
0%
#35
1%
#40
0%
1$
0#
#45
1!
0"
1%
#50
0%
#55
1%
#60
0%
1#
#65
0!
1"
1%
#70
0%
#75
1!
0"
1%
#80
0%
0$
0#
