FLIPFLOPS/RS_flipflop/rs.v
// RS Flip-Flop Module
module rs_flipflop (
    input R,        // Reset input
    input S,        // Set input
    input clk,      // Clock input
    input rst,      // Asynchronous reset
    output reg Q,   // Output Q
    output reg Qn   // Output Qn (Q not)
);
    always @(posedge clk or posedge rst) begin
        if (rst) begin
            Q <= 0;
            Qn <= 1;
        end else begin
            case ({S, R})
                2'b00: begin
                    Q <= Q;    // No change
                    Qn <= Qn;
                end
                2'b01: begin
                    Q <= 0;    // Reset Q
                    Qn <= 1;
                end
                2'b10: begin
                    Q <= 1;    // Set Q
                    Qn <= 0;
                end
                2'b11: begin
                    Q <= 1;    // Invalid state in RS Flip-Flop, but can be treated as set
                    Qn <= 0;
                end
            endcase
        end
    end
endmodule

FLIPFLOPS/RS_flipflop/rs_tb.v
// Testbench for RS Flip-Flop with VCD generation
module tb_rs_flipflop;
    // Signals for RS Flip-Flop
    reg R, S, clk, rst;
    wire Q, Qn;

    // Instantiate the RS Flip-Flop
    rs_flipflop uut (
        .R(R),
        .S(S),
        .clk(clk),
        .rst(rst),
        .Q(Q),
        .Qn(Qn)
    );

    // Clock generation
    always begin
        #5 clk = ~clk; // Generate clock with 10-time unit period
    end

    // VCD file generation
    initial begin
        // Initialize signals
        clk = 0;
        rst = 0;
        R = 0;
        S = 0;

        // Open VCD file
        $dumpfile("rs_waveform.vcd");
        $dumpvars(0, tb_rs_flipflop);

        // Apply reset
        rst = 1; #10;
        rst = 0; #10;

        // Test RS Flip-Flop behavior
        S = 1; R = 0; #20; // Set Q
        S = 0; R = 1; #20; // Reset Q
        S = 0; R = 0; #20; // No change
        S = 1; R = 1; #20; // Invalid state (can treat as Set)

        // Finish the simulation
        $finish;
    end
endmodule

FLIPFLOPS/RS_flipflop/rs_waveform.vcd
$date
	Tue Mar 18 11:13:42 2025
$end
$version
	Icarus Verilog
$end
$timescale
	1s
$end
$scope module tb_rs_flipflop $end
$var wire 1 ! Qn $end
$var wire 1 " Q $end
$var reg 1 # R $end
$var reg 1 $ S $end
$var reg 1 % clk $end
$var reg 1 & rst $end
$scope module uut $end
$var wire 1 # R $end
$var wire 1 $ S $end
$var wire 1 % clk $end
$var wire 1 & rst $end
$var reg 1 " Q $end
$var reg 1 ! Qn $end
$upscope $end
$upscope $end
$enddefinitions $end
$comment Show the parameter values. $end
$dumpall
$end
#0
$dumpvars
1&
0%
0$
0#
0"
1!
$end
#5
1%
#10
0%
0&
#15
1%
#20
0%
1$
#25
0!
1"
1%
#30
0%
#35
1%
#40
0%
1#
0$
#45
1!
0"
1%
#50
0%
#55
1%
#60
0%
0#
#65
1%
#70
0%
#75
1%
#80
0%
1#
1$
#85
0!
1"
1%
