FLIPFLOPS/T_flipflop/t.v
// T Flip-Flop Module
module t_flipflop (
    input T,        // Toggle input
    input clk,      // Clock input
    input rst,      // Asynchronous reset
    output reg Q,   // Output Q
    output reg Qn   // Output Qn (Q not)
);
    always @(posedge clk or posedge rst) begin
        if (rst) begin
            Q <= 0;
            Qn <= 1;
        end else begin
            if (T) begin
                Q <= ~Q;    // Toggle Q
                Qn <= ~Qn;  // Toggle Qn
            end
        end
    end
endmodule

FLIPFLOPS/T_flipflop/t_tb.v
// Testbench for T Flip-Flop with VCD generation
module tb_t_flipflop;
    // Signals for T Flip-Flop
    reg T, clk, rst;
    wire Q, Qn;

    // Instantiate the T Flip-Flop
    t_flipflop uut (
        .T(T),
        .clk(clk),
        .rst(rst),
        .Q(Q),
        .Qn(Qn)
    );

    // Clock generation
    always begin
        #5 clk = ~clk; // Generate clock with 10-time unit period
    end

    // VCD file generation
    initial begin
        // Initialize signals
        clk = 0;
        rst = 0;
        T = 0;

        // Open VCD file
        $dumpfile("t_waveform.vcd");
        $dumpvars(0, tb_t_flipflop);

        // Apply reset
        rst = 1; #10;
        rst = 0; #10;

        // Test T Flip-Flop behavior
        T = 1; #20; // Toggle Q
        T = 0; #20; // No change
        T = 1; #20; // Toggle Q again

        // Finish the simulation
        $finish;
    end
endmodule

FLIPFLOPS/T_flipflop/t_waveform.vcd
$date
	Tue Mar 18 11:15:00 2025
$end
$version
	Icarus Verilog
$end
$timescale
	1s
$end
$scope module tb_t_flipflop $end
$var wire 1 ! Qn $end
$var wire 1 " Q $end
$var reg 1 # T $end
$var reg 1 $ clk $end
$var reg 1 % rst $end
$scope module uut $end
$var wire 1 # T $end
$var wire 1 $ clk $end
$var wire 1 % rst $end
$var reg 1 " Q $end
$var reg 1 ! Qn $end
$upscope $end
$upscope $end
$enddefinitions $end
$comment Show the parameter values. $end
$dumpall
$end
#0
$dumpvars
1%
0$
0#
0"
1!
$end
#5
1$
#10
0$
0%
#15
1$
#20
0$
1#
#25
0!
1"
1$
#30
0$
#35
1!
0"
1$
#40
0$
0#
#45
1$
#50
0$
#55
1$
#60
0$
1#
#65
0!
1"
1$
#70
0$
#75
1!
0"
1$
